paulius_employee_module/__init__.py
paulius_employee_module/employee.py
paulius_employee_module/main.py
paulius_employee_module/subpackage/__init__.py
paulius_employee_module-0.1.4.dist-info/METADATA
paulius_employee_module-0.1.4.dist-info/WHEEL
paulius_employee_module-0.1.4.dist-info/top_level.txt
paulius_employee_module-0.1.4.dist-info/RECORD
